robometrics/__init__.py
robometrics/lib/__init__.py
robometrics/lib/register.py
robometrics/models/__init__.py
robometrics/models/metrics.py
robometrics/server/IntakeAndServe.py
robometrics/server/__init__.py
robometrics/worker/__init__.py
robometrics/worker/worker.py
src/__init__.py
src/lib/__init__.py
src/lib/register.py
src/models/__init__.py
src/models/metrics.py
src/server/IntakeAndServe.py
src/server/__init__.py
src/worker/__init__.py
src/worker/worker.py
roborregos_metrics_client-2.2.0.dist-info/METADATA
roborregos_metrics_client-2.2.0.dist-info/WHEEL
roborregos_metrics_client-2.2.0.dist-info/entry_points.txt
roborregos_metrics_client-2.2.0.dist-info/top_level.txt
roborregos_metrics_client-2.2.0.dist-info/RECORD
