Metadata-Version: 2.1
Name: roborregos-metrics-client
Version: 2.2.0
Summary: UNKNOWN
Home-page: UNKNOWN
License: UNKNOWN
Platform: UNKNOWN
Requires-Dist: psutil
Requires-Dist: pydantic
Requires-Dist: requests
